gs_quant/__init__.py
gs_quant/_version.py
gs_quant/base.py
gs_quant/common.py
gs_quant/config.ini
gs_quant/context_base.py
gs_quant/errors.py
gs_quant/json_convertors.py
gs_quant/json_convertors_common.py
gs_quant/json_encoder.py
gs_quant/priceable.py
gs_quant/session.py
gs_quant/analytics/__init__.py
gs_quant/analytics/common/__init__.py
gs_quant/analytics/common/constants.py
gs_quant/analytics/common/enumerators.py
gs_quant/analytics/common/helpers.py
gs_quant/analytics/core/__init__.py
gs_quant/analytics/core/processor.py
gs_quant/analytics/core/processor_result.py
gs_quant/analytics/core/query_helpers.py
gs_quant/analytics/datagrid/__init__.py
gs_quant/analytics/datagrid/data_cell.py
gs_quant/analytics/datagrid/data_column.py
gs_quant/analytics/datagrid/data_row.py
gs_quant/analytics/datagrid/datagrid.py
gs_quant/analytics/datagrid/serializers.py
gs_quant/analytics/datagrid/utils.py
gs_quant/analytics/processors/__init__.py
gs_quant/analytics/processors/analysis_processors.py
gs_quant/analytics/processors/econometrics_processors.py
gs_quant/analytics/processors/scale_processors.py
gs_quant/analytics/processors/special_processors.py
gs_quant/analytics/processors/statistics_processors.py
gs_quant/analytics/processors/utility_processors.py
gs_quant/analytics/workspaces/__init__.py
gs_quant/analytics/workspaces/components.py
gs_quant/analytics/workspaces/workspace.py
gs_quant/api/__init__.py
gs_quant/api/api_cache.py
gs_quant/api/api_session.py
gs_quant/api/data.py
gs_quant/api/risk.py
gs_quant/api/utils.py
gs_quant/api/fred/__init__.py
gs_quant/api/fred/data.py
gs_quant/api/fred/fred_query.py
gs_quant/api/gs/__init__.py
gs_quant/api/gs/assets.py
gs_quant/api/gs/backtests.py
gs_quant/api/gs/base_screener.py
gs_quant/api/gs/carbon.py
gs_quant/api/gs/content.py
gs_quant/api/gs/countries.py
gs_quant/api/gs/data.py
gs_quant/api/gs/data_screen.py
gs_quant/api/gs/datagrid.py
gs_quant/api/gs/esg.py
gs_quant/api/gs/federated_secmaster.py
gs_quant/api/gs/groups.py
gs_quant-1.4.80.dist-info/licenses/LICENSE
gs_quant-1.4.80.dist-info/licenses/NOTICE
gs_quant-1.4.80.dist-info/licenses/NOTICE.txt
gs_quant-1.4.80.dist-info/METADATA
gs_quant-1.4.80.dist-info/WHEEL
gs_quant-1.4.80.dist-info/top_level.txt
gs_quant-1.4.80.dist-info/RECORD
