Metadata-Version: 2.4
Name: gs_quant
Version: 1.4.80
Summary: Goldman Sachs Quant
Author-email: Goldman Sachs <developer@gs.com>
License: Apache-2.0
Project-URL: Homepage, https://marquee.gs.com
Classifier: Programming Language :: Python :: 3
Classifier: Programming Language :: Python :: 3.9
Classifier: Programming Language :: Python :: 3.10
Classifier: Programming Language :: Python :: 3.11
Classifier: Programming Language :: Python :: 3.12
Classifier: Programming Language :: Python :: 3.13
Classifier: Operating System :: OS Independent
Classifier: License :: OSI Approved :: Apache Software License
Requires-Python: >=3.9
License-File: LICENSE
License-File: NOTICE
License-File: NOTICE.txt
Requires-Dist: aenum
Requires-Dist: backoff
Requires-Dist: backports.zoneinfo; python_version < "3.9"
Requires-Dist: cachetools
Requires-Dist: certifi
Requires-Dist: dataclasses_json
Requires-Dist: deprecation
Requires-Dist: inflection
Requires-Dist: lmfit
Requires-Dist: more_itertools
Requires-Dist: msgpack
Requires-Dist: nest-asyncio
Requires-Dist: numpy<2.4.0,>1.17.0
Requires-Dist: opentelemetry-api
Requires-Dist: opentelemetry-sdk
Requires-Dist: pandas<3.0.0,>=1.4
Requires-Dist: pydash<7.0.0
Requires-Dist: python-dateutil>=2.7.0
Requires-Dist: requests
Requires-Dist: httpx>=0.28.1
Requires-Dist: scipy>=1.2.0
Requires-Dist: statsmodels>=0.13.0
Requires-Dist: tqdm
Requires-Dist: websockets
Provides-Extra: turbo
Requires-Dist: quant-extensions; extra == "turbo"
Provides-Extra: notebook
Requires-Dist: jupyter; extra == "notebook"
Requires-Dist: matplotlib; extra == "notebook"
Requires-Dist: seaborn; extra == "notebook"
Requires-Dist: treelib; extra == "notebook"
Provides-Extra: test
Requires-Dist: pytest; extra == "test"
Requires-Dist: pytest-cov; extra == "test"
Requires-Dist: pytest-mock; extra == "test"
Requires-Dist: pytest-order; extra == "test"
Requires-Dist: pytest-asyncio; extra == "test"
Requires-Dist: testfixtures; extra == "test"
Requires-Dist: nbconvert; extra == "test"
Requires-Dist: nbformat; extra == "test"
Requires-Dist: plotly; extra == "test"
Requires-Dist: freezegun; extra == "test"
Requires-Dist: ruff; extra == "test"
Provides-Extra: develop
Requires-Dist: wheel; extra == "develop"
Requires-Dist: sphinx; extra == "develop"
Requires-Dist: sphinx_rtd_theme; extra == "develop"
Requires-Dist: sphinx_autodoc_typehints; extra == "develop"
Requires-Dist: pytest; extra == "develop"
Requires-Dist: pytest-cov; extra == "develop"
Requires-Dist: pytest-mock; extra == "develop"
Requires-Dist: pytest-order; extra == "develop"
Requires-Dist: testfixtures; extra == "develop"
Dynamic: license-file
